urbanairship/__about__.py
urbanairship/__init__.py
urbanairship/client.py
urbanairship/common.py
urbanairship/core.py
urbanairship/enums.py
urbanairship/py.typed
urbanairship/urls.py
urbanairship/automation/__init__.py
urbanairship/automation/core.py
urbanairship/automation/pipeline.py
urbanairship/custom_events/__init__.py
urbanairship/custom_events/custom_events.py
urbanairship/devices/__init__.py
urbanairship/devices/attributes.py
urbanairship/devices/channel_uninstall.py
urbanairship/devices/devicelist.py
urbanairship/devices/email.py
urbanairship/devices/named_users.py
urbanairship/devices/open_channel.py
urbanairship/devices/segment.py
urbanairship/devices/sms.py
urbanairship/devices/static_lists.py
urbanairship/devices/subscription_lists.py
urbanairship/devices/tag.py
urbanairship/devices/tag_lists.py
urbanairship/experiments/__init__.py
urbanairship/experiments/core.py
urbanairship/experiments/experiment.py
urbanairship/experiments/variant.py
urbanairship/push/__init__.py
urbanairship/push/audience.py
urbanairship/push/core.py
urbanairship/push/payload.py
urbanairship/push/schedule.py
urbanairship/push/template.py
urbanairship/reports/__init__.py
urbanairship/reports/experiments.py
urbanairship/reports/reports.py
urbanairship-7.3.0.dist-info/licenses/AUTHORS
urbanairship-7.3.0.dist-info/licenses/LICENSE
urbanairship-7.3.0.dist-info/METADATA
urbanairship-7.3.0.dist-info/WHEEL
urbanairship-7.3.0.dist-info/top_level.txt
urbanairship-7.3.0.dist-info/RECORD
