Metadata-Version: 2.4
Name: urbanairship
Version: 7.3.0
Summary: ``urbanairship`` is a Python library for using the Airship REST
Home-page: https://airship.com/
Author: Airship Tools
Author-email: tools@airship.com
License: BSD License
Project-URL: Documentation, https://docs.airship.com/
Project-URL: Source, https://github.com/urbanairship/python-library
Project-URL: Tracker, https://github.com/urbanairship/python-library/issues
Classifier: Development Status :: 5 - Production/Stable
Classifier: Environment :: Web Environment
Classifier: Intended Audience :: Developers
Classifier: License :: OSI Approved :: Apache Software License
Classifier: Operating System :: OS Independent
Classifier: Programming Language :: Python
Classifier: Programming Language :: Python :: 3
Classifier: Programming Language :: Python :: 3.10
Classifier: Programming Language :: Python :: 3.11
Classifier: Programming Language :: Python :: 3.12
Classifier: Programming Language :: Python :: 3.13
Classifier: Topic :: Software Development :: Libraries
Requires-Python: >=3.10
License-File: LICENSE
License-File: AUTHORS
Requires-Dist: requests>=2.32
Requires-Dist: six
Requires-Dist: backoff>=2.2.1
Requires-Dist: pyjwt>=2.8.0
Provides-Extra: test
Requires-Dist: pytest>=7.0.0; extra == "test"
Requires-Dist: pytest-cov>=4.0.0; extra == "test"
Requires-Dist: mock>=5.0.0; extra == "test"
Provides-Extra: dev
Requires-Dist: pytest>=7.0.0; extra == "dev"
Requires-Dist: pytest-cov>=4.0.0; extra == "dev"
Requires-Dist: mock>=5.0.0; extra == "dev"
Requires-Dist: black; extra == "dev"
Requires-Dist: isort; extra == "dev"
Requires-Dist: flake8; extra == "dev"
Dynamic: author
Dynamic: author-email
Dynamic: classifier
Dynamic: home-page
Dynamic: license
Dynamic: license-file
Dynamic: project-url
Dynamic: provides-extra
Dynamic: requires-dist
Dynamic: requires-python
